{
  "calendar": [
    {
      "day": "Monday",
      "time": "10:45 AM",
      "event": "OT",
      "duration": 4,
      "category": "appt",
      "member": "Leo"
    },
    {
      "day": ["Monday", "Tuesday", "Wednesday", "Thursday", "Friday"],
      "time": "8:00 AM",
      "event": "Work",
      "duration": 36,
      "category": "work",
      "member": "Cole"
    },
    {
      "day": "Tuesday",
      "time": "6:00 PM",
      "event": "Tournament",
      "duration": 8,
      "category": "house",
      "member": "Cole"
    },
    {
      "day": "Wednesday",
      "time": "12:00 PM",
      "event": "Preschool",
      "duration": 10,
      "category": "school",
      "member": "Leo"
    },
    {
      "day": "Friday",
      "time": "12:00 PM",
      "event": "Good Friday - No school",
      "duration": 10,
      "category": "school",
      "member": "Leo"
    },
    {
      "day": ["Tuesday", "Thursday"],
      "time": "10:00 AM",
      "event": "with dad",
      "duration": 44,
      "category": "other",
      "member": "Leo"
    },
    {
      "day": ["Tuesday", "Thursday"],
      "time": "11:00 AM",
      "event": "Work",
      "duration": 24,
      "category": "work",
      "member": "Autumn"
    },

    {
      "day": ["Wednesday", "Friday"],
      "time": "12:15 PM",
      "event": "Work",
      "duration": 8,
      "category": "work",
      "member": "Autumn"
    },
    {
      "day": ["Monday", "Thursday"],
      "time": "9:00 PM",
      "event": "Homework",
      "duration": 8,
      "category": "school",
      "member": "Autumn"
    },
    {
      "day": ["Monday", "Thursday"],
      "time": "9:00 PM",
      "event": "Server Maintenance",
      "duration": 8,
      "category": "house",
      "member": "Cole"
    },
    {
      "day": "Thursday",
      "time": "9:30 AM",
      "event": "Doctor Appt",
      "duration": 6,
      "category": "appt",
      "member": "Leo"
    }
    
  ],
  "dinners": {
    "Monday": [
      "Lasagna",
      "Garlic Bread"
    ],
    "Tuesday": [
      "Chicken and Rice"
    ],
    "Wednesday": [
      "Free for All"
    ],
    "Thursday": [
      "Chicken Patty Sandwiches",
      "Curly Fries"
    ],
    "Friday": [
      "Pizza Friday"
    ],
    "Saturday": [
      "free for all"
    ],
    "Sunday": [
      "Beef Stew"
    ]
  },
  "birthdays": {
    "January": [
      { "name": "Kevin", "date": "16th" },
      { "name": "Dason", "date": "17th" },
      { "name": "Jessica", "date": "19th" },
      { "name": "Autumn", "date": "29th" }
    ],
    "February": [
      { "name": "Cole D", "date": "13th" },
      { "name": "Cole S", "date": "18th" }
    ],
    "March": [
      { "name": "Aeristy", "date": "2nd" },
      { "name": "Melinda", "date": "2nd" },
      { "name": "Quorra", "date": "10th" },
      { "name": "Leon", "date": "14th" },
      { "name": "Teresa-Mom-Gma", "date": "24th" }
    ],
    "April": [
      { "name": "Cynthia", "date": "9th" },
      { "name": "Lily", "date": "12th" },
      { "name": "Becky", "date": "25th" },
      { "name": "Farren", "date": "30th" }
    ],
    "May": [
      { "name": "Cory", "date": "22nd" },
      { "name": "Gideon", "date": "29th" },
      { "name": "Carson", "date": "30th" }
    ],
    "June": [
      { "name": "Mark-Dad-Gpa", "date": "17th" }
    ],
    "July": [
      { "name": "Josie", "date": "25th" }
    ],
    "August": [
      { "name": "Dalen", "date": "15th" }
    ],
    "September": [
      { "name": "Mya", "date": "3rd" },
      { "name": "Jay", "date": "4th" },
      { "name": "Josh", "date": "4th" },
      { "name": "Grimm", "date": "20th" }
    ],
    "October": [
      { "name": "Damian", "date": "1st" },
      { "name": "Cole Jr", "date": "12th" },
      { "name": "Chad", "date": "13th" },
      { "name": "Lisa", "date": "13th" },
      { "name": "Samantha", "date": "22nd" }
    ],
    "November": [
      { "name": "", "date": null }
    ],
    "December": [
      { "name": "Cassie", "date": 8 },
      { "name": "Tonya", "date": 12 }
    ]
  },
  "chores": {
    "Monday": [
      "Living Room",
      "Trash"
    ],
    "Tuesday": [
      "Office"
    ],
    "Wednesday": [
      "Kitchen"
    ],
    "Thursday": [
      "Bathrooms"
    ],
    "Friday": [
      "Miscellaneous"
    ],
    "Saturday": [
      "free day"
    ],
    "Sunday": [
      "Bedrooms",
      "Laundry"
    ]
  },
  "reminders": {
    "Monday": {
      "title": "Heads up!",
      "message": "Trash gets picked up tomorrow morning!"
    },
    "Saturday": {
      "title": "Heads up!",
      "message": "Groceries will be ordered tomorrow<br>Make sure to add to the list!"
    },
    "Sunday": {
      "title": "Heads up!",
      "message": "Groceries are being ordered today<br>Make sure to add to the list!"
    },
    "Thursday": {
      "title": "Heads up!",
      "message": "No school tomorrow - Good Friday"
    }
  }
}
